pidcon/__init__.py
pidcon/pidcon.py
pidcon-0.1.0.dist-info/LICENSE
pidcon-0.1.0.dist-info/METADATA
pidcon-0.1.0.dist-info/WHEEL
pidcon-0.1.0.dist-info/top_level.txt
pidcon-0.1.0.dist-info/RECORD
