Metadata-Version: 2.1
Name: pidcon
Version: 0.1.0
Summary: A package to handle simple PID controller
Home-page: https://github.com/FutureTech-o/pidcon
Author: Akram Abu Owaimer
Author-email: Akram.AbuOwaimer@gmail.com
License: UNKNOWN
Platform: UNKNOWN
Classifier: Programming Language :: Python :: 3.7
Classifier: License :: OSI Approved :: GNU General Public License v3 (GPLv3)
Requires-Python: >3.3
Requires-Dist: Events (==0.3)
